{"fundamentals":{"marketCapB":0.245,"targetPrice":4.5,"avgVolume":86803.0,"volume":464057.754932,"prevClose":3.13,"week52High":9.55,"week52Low":1.84,"exchange":"NYSE","salesB":2.762,"grossProfitB":1.289,"operIncomeB":0.027,"incomeB":-1.101,"cashB":0.282,"assetsB":2.452,"liabilitiesB":2.913,"equityB":-0.461,"debtB":2.05,"currentRatio":57.85,"quickRatio":49.99,"grossMargin":46.68,"operMargin":0.99,"profitMargin":-39.85,"roe":238.76,"epsTtm":0.68,"epsNextY":0.36,"epsNextQ":-0.13,"sharesB":0.077,"pe":4.71,"forwardPE":8.89,"ps":0.09,"debtEq":-4.45,"source":"nasdaq"},"news":[{"title":"Alchemy Pay Adds Illinois License as U.S. Regulatory Coverage Reaches 18 States","publisher":"CryptoProwl","link":"https://finance.yahoo.com/m/481da432-e15f-3c57-9a71-7c76abbd1bc4/alchemy-pay-adds-illinois.html","publishedAt":"2026-06-25"},{"title":"Accendra Health Reports Expiration of Exchange Offers, Final Tender Results","publisher":"MT Newswires","link":"https://finance.yahoo.com/healthcare/articles/accendra-health-reports-expiration-exchange-120701942.html","publishedAt":"2026-06-24"},{"title":"Accendra Health Announces Expiration and Final Results of Offers and Consent Solicitations","publisher":"Business Wire","link":"https://finance.yahoo.com/healthcare/articles/accendra-health-announces-expiration-final-011500683.html","publishedAt":"2026-06-24"},{"title":"Accendra Health Announces Early Results of Exchange Offers","publisher":"MT Newswires","link":"https://finance.yahoo.com/markets/stocks/articles/accendra-health-announces-early-results-111802951.html","publishedAt":"2026-06-10"},{"title":"Accendra Health Announces Early Results of Offers and Consent Solicitations","publisher":"Business Wire","link":"https://finance.yahoo.com/markets/stocks/articles/accendra-health-announces-early-results-103000040.html","publishedAt":"2026-06-10"},{"title":"Are Options Traders Betting on a Big Move in Accendra Health Stock?","publisher":"Zacks","link":"https://finance.yahoo.com/markets/options/articles/options-traders-betting-big-move-124800851.html","publishedAt":"2026-05-28"},{"title":"Owens & Minor Appoints Jim Marshall as Chief Executive Officer","publisher":"PR Newswire","link":"https://finance.yahoo.com/sectors/healthcare/articles/owens-minor-appoints-jim-marshall-140000204.html","publishedAt":"2026-05-27"},{"title":"Accendra Health Launches Offering to Exchange Senior Notes","publisher":"MT Newswires","link":"https://finance.yahoo.com/markets/stocks/articles/accendra-health-launches-offering-exchange-201734505.html","publishedAt":"2026-05-23"}],"ticker":"ACH","company":"Accendra Health Inc.","historySource":"snapshot","earningsHistory":[{"date":"2023-08-04","epsActual":0.18,"epsEstimate":0.18,"surprisePct":1.07},{"date":"2023-11-03","epsActual":0.44,"epsEstimate":0.38,"surprisePct":17.29},{"date":"2024-02-20","epsActual":0.69,"epsEstimate":0.66,"surprisePct":4.02},{"date":"2024-05-03","epsActual":0.19,"epsEstimate":0.18,"surprisePct":5.88},{"date":"2024-08-02","epsActual":0.36,"epsEstimate":0.33,"surprisePct":7.58},{"date":"2024-11-04","epsActual":0.42,"epsEstimate":0.41,"surprisePct":1.41},{"date":"2025-02-28","epsActual":0.55,"epsEstimate":0.52,"surprisePct":5.68},{"date":"2025-05-08","epsActual":0.23,"epsEstimate":0.2,"surprisePct":14.45},{"date":"2025-08-11","epsActual":0.26,"epsEstimate":0.28,"surprisePct":-5.73},{"date":"2025-10-30","epsActual":0.25,"epsEstimate":0.23,"surprisePct":6.39},{"date":"2026-02-19","epsActual":0.21,"epsEstimate":0.22,"surprisePct":-5.13},{"date":"2026-05-11","epsActual":-0.04,"epsEstimate":-0.1,"surprisePct":59.31}]}