{"fundamentals":{"marketCapB":2.163,"targetPrice":226.0,"avgVolume":49723.0,"volume":113607.686302,"prevClose":194.44,"week52High":210.64,"week52Low":136.57,"exchange":"NYSE","salesB":1.63,"incomeB":0.207,"cashB":18.481,"assetsB":35.37,"liabilitiesB":33.651,"equityB":1.719,"debtB":0.022,"currentRatio":NaN,"quickRatio":NaN,"grossMargin":0.0,"operMargin":0.0,"profitMargin":12.73,"roe":12.07,"epsTtm":17.24,"epsNextY":19.89,"epsNextQ":4.98,"sharesB":0.011,"pe":11.56,"forwardPE":10.02,"ps":1.33,"pb":1.26,"debtEq":0.01,"source":"nasdaq"},"news":[{"title":"3 Mortgage & Related Services Stocks to Watch Despite Industry Weakness","publisher":"Zacks","link":"https://finance.yahoo.com/real-estate/articles/3-mortgage-related-services-stocks-134700748.html","publishedAt":"2026-06-30"},{"title":"Are Finance Stocks Lagging  NewtekOne, Inc. (NEWT) This Year?","publisher":"Zacks","link":"https://finance.yahoo.com/markets/stocks/articles/finance-stocks-lagging-newtekone-inc-134007857.html","publishedAt":"2026-06-29"},{"title":"Improve Your Retirement Income with These 3 Top-Ranked Dividend Stocks","publisher":"Zacks","link":"https://finance.yahoo.com/markets/stocks/articles/improve-retirement-income-3-top-131005722.html","publishedAt":"2026-06-29"},{"title":"Implied Volatility Surging for Federal Agricultural Mortgage Stock Options","publisher":"Zacks","link":"https://finance.yahoo.com/markets/options/articles/implied-volatility-surging-federal-agricultural-132600861.html","publishedAt":"2026-06-23"},{"title":"3 Top-Ranked Dividend Stocks: A Smarter Way to Boost Your Retirement Income","publisher":"Zacks","link":"https://finance.yahoo.com/markets/stocks/articles/3-top-ranked-dividend-stocks-131002630.html","publishedAt":"2026-06-15"},{"title":"A Look At Federal Agricultural Mortgage (AGM) Valuation As CEO Succession Draws Fresh Investor Attention","publisher":"Simply Wall St.","link":"https://finance.yahoo.com/markets/stocks/articles/look-federal-agricultural-mortgage-agm-011641419.html","publishedAt":"2026-06-12"},{"title":"Are Finance Stocks Lagging  Federal Agricultural Mortgage (AGM) This Year?","publisher":"Zacks","link":"https://finance.yahoo.com/markets/stocks/articles/finance-stocks-lagging-federal-agricultural-134004528.html","publishedAt":"2026-06-11"},{"title":"Federal Agricultural Mortgage Sets July 1 for CEO Transition as Carpenter Succeeds Nordholm","publisher":"MT Newswires","link":"https://finance.yahoo.com/sectors/healthcare/articles/federal-agricultural-mortgage-sets-july-202945950.html","publishedAt":"2026-06-09"}],"ticker":"AGM","company":"Federal Agricultural Mortgage Corporation","historySource":"snapshot","earningsHistory":[{"date":"2023-08-07","epsActual":3.86,"epsEstimate":3.23,"surprisePct":19.5},{"date":"2023-11-06","epsActual":4.13,"epsEstimate":4.0,"surprisePct":3.16},{"date":"2024-02-23","epsActual":4.1,"epsEstimate":4.05,"surprisePct":1.32},{"date":"2024-05-06","epsActual":3.96,"epsEstimate":4.06,"surprisePct":-2.46},{"date":"2024-08-05","epsActual":3.63,"epsEstimate":4.08,"surprisePct":-11.03},{"date":"2024-11-04","epsActual":4.1,"epsEstimate":4.11,"surprisePct":-0.32},{"date":"2025-02-21","epsActual":3.97,"epsEstimate":4.17,"surprisePct":-4.87},{"date":"2025-05-09","epsActual":4.19,"epsEstimate":4.06,"surprisePct":3.2},{"date":"2025-08-07","epsActual":4.32,"epsEstimate":4.29,"surprisePct":0.7},{"date":"2025-11-03","epsActual":4.44,"epsEstimate":4.58,"surprisePct":-3.06},{"date":"2026-02-19","epsActual":3.66,"epsEstimate":4.53,"surprisePct":-19.15},{"date":"2026-05-05","epsActual":4.74,"epsEstimate":4.44,"surprisePct":6.68}]}