{"fundamentals":{"sharesB":0.007,"source":"nasdaq"},"news":[{"title":"All In FutureTech Alliance Inc. Announces the Election of Prominent AI Technology Investor and Influential Content Creator Li Shanglong as New Chairman, Along With Certain Management Changes","publisher":"GlobeNewswire","link":"https://finance.yahoo.com/technology/ai/articles/futuretech-alliance-inc-announces-election-144500412.html","publishedAt":"2026-06-17"},{"title":"AIFA Issues Formal Clarification and Refutation Regarding the Share Acquisition Transaction Involving HyalRoute Communication Group Limited","publisher":"GlobeNewswire","link":"https://finance.yahoo.com/markets/stocks/articles/aifa-issues-formal-clarification-refutation-142900978.html","publishedAt":"2026-06-08"},{"title":"Allied Gaming & Entertainment: Q4 Earnings Snapshot","publisher":"Associated Press","link":"https://finance.yahoo.com/markets/stocks/articles/allied-gaming-entertainment-q4-earnings-110422144.html","publishedAt":"2026-05-22"}],"ticker":"AIFA","company":"All In FutureTech Alliance Inc.","historySource":"snapshot"}