{"fundamentals":{"marketCapB":0.02,"avgVolume":448136.0,"volume":84686.030461,"prevClose":1.29,"week52High":3.63,"week52Low":0.6175,"exchange":"NASDAQ-CM","salesB":0.001,"grossProfitB":0.001,"operIncomeB":-0.009,"incomeB":-0.02,"cashB":0.003,"assetsB":0.01,"liabilitiesB":0.003,"equityB":0.008,"debtB":0,"currentRatio":142.85,"quickRatio":139.02,"grossMargin":56.48,"operMargin":-775.48,"profitMargin":-1740.98,"roe":-260.34,"sharesB":0.016,"ps":20.0,"pb":2.5,"debtEq":0.0,"source":"nasdaq"},"news":[{"title":"Firefly’s AI-Driven Evoke System Powers Discovery of Novel Electrophysiological Biomarker for PTSD","publisher":"GlobeNewswire","link":"https://finance.yahoo.com/sectors/healthcare/articles/firefly-ai-driven-evoke-system-114000579.html","publishedAt":"2026-06-02"},{"title":"With Brain Scan Volume Momentum Accelerating, Firefly Makes History by Building the World’s First Known 200,000+ Standardized EEG/ERP Depository","publisher":"GlobeNewswire","link":"https://finance.yahoo.com/sectors/healthcare/articles/brain-scan-volume-momentum-accelerating-114500821.html","publishedAt":"2026-04-13"}],"ticker":"AIFF","company":"Firefly Neuroscience Inc.","historySource":"snapshot"}