{"fundamentals":{"marketCapB":0.111,"targetPrice":1.54,"avgVolume":71300.0,"volume":30981.94896,"prevClose":1.16,"week52High":3.1,"week52Low":1.01,"exchange":"NASDAQ-GM","salesB":0.437,"grossProfitB":0.252,"operIncomeB":-0.005,"incomeB":-0.004,"cashB":0.079,"assetsB":0.201,"liabilitiesB":0.189,"equityB":0.012,"debtB":0,"currentRatio":160.63,"quickRatio":101.54,"grossMargin":57.49,"operMargin":-1.23,"profitMargin":-0.83,"roe":-29.55,"epsTtm":-0.36,"epsNextY":0.01,"epsNextQ":-0.03,"sharesB":0.101,"forwardPE":110.0,"ps":0.25,"pb":9.25,"debtEq":0.0,"source":"nasdaq"},"news":[{"title":"Brilliant Earth Group Bets on Fine Jewelry and Showrooms to Spark Growth","publisher":"MarketBeat","link":"https://finance.yahoo.com/m/885fcb2d-63e4-3ac6-aac9-6c8f6b2c6cba/brilliant-earth-group-bets-on.html","publishedAt":"2026-06-03"},{"title":"Why The Brilliant Earth Group (BRLT) Story Is Shifting As Margin Concerns Build","publisher":"Simply Wall St.","link":"https://finance.yahoo.com/markets/stocks/articles/why-brilliant-earth-group-brlt-131117057.html","publishedAt":"2026-05-28"},{"title":"Brilliant Earth Announces Participation in Upcoming Investor Conferences","publisher":"GlobeNewswire","link":"https://finance.yahoo.com/news/brilliant-earth-announces-participation-upcoming-200500600.html","publishedAt":"2026-05-14"},{"title":"Brilliant Earth Group Q1 Earnings Call Highlights","publisher":"MarketBeat","link":"https://finance.yahoo.com/m/8c5f66ce-86b0-3ed5-8c33-f4a61f7d911b/brilliant-earth-group-q1.html","publishedAt":"2026-05-07"},{"title":"Brilliant Earth (BRLT) Q1 2026 Earnings Transcript","publisher":"Motley Fool","link":"https://finance.yahoo.com/m/2dd77b5c-a653-3413-bad7-74cb8ecba63e/brilliant-earth-%28brlt%29-q1.html","publishedAt":"2026-05-07"},{"title":"Brilliant Earth Group, Inc. (BRLT) Reports Q1 Loss, Beats Revenue Estimates","publisher":"Zacks","link":"https://finance.yahoo.com/markets/stocks/articles/brilliant-earth-group-inc-brlt-223007202.html","publishedAt":"2026-05-07"},{"title":"Brilliant Earth Reports First Quarter Results","publisher":"GlobeNewswire","link":"https://finance.yahoo.com/markets/stocks/articles/brilliant-earth-reports-first-quarter-200500103.html","publishedAt":"2026-05-07"},{"title":"Brilliant Earth to Report First Quarter 2026 Financial Results on May 6th","publisher":"GlobeNewswire","link":"https://finance.yahoo.com/markets/stocks/articles/brilliant-earth-report-first-quarter-200500968.html","publishedAt":"2026-04-16"}],"ticker":"BRLT","company":"Brilliant Earth Group Inc. Class A","historySource":"snapshot","earningsHistory":[{"date":"2023-05-11","epsActual":0.03,"epsEstimate":0.01,"surprisePct":105.48},{"date":"2023-08-09","epsActual":0.04,"epsEstimate":0.03,"surprisePct":47.55},{"date":"2023-11-09","epsActual":0.05,"epsEstimate":0.04,"surprisePct":34.41},{"date":"2024-03-14","epsActual":0.04,"epsEstimate":0.01,"surprisePct":456.33},{"date":"2024-05-09","epsActual":0.03,"epsEstimate":null,"surprisePct":null},{"date":"2024-08-08","epsActual":0.03,"epsEstimate":null,"surprisePct":588.07},{"date":"2024-11-07","epsActual":0.02,"epsEstimate":null,"surprisePct":789.66},{"date":"2025-03-12","epsActual":0.04,"epsEstimate":null,"surprisePct":1398.7},{"date":"2025-08-07","epsActual":0.01,"epsEstimate":-0.01,"surprisePct":186.73},{"date":"2025-11-05","epsActual":0.02,"epsEstimate":0.02,"surprisePct":11.11},{"date":"2026-03-05","epsActual":-0.06,"epsEstimate":0.02,"surprisePct":-427.33},{"date":"2026-05-06","epsActual":-0.05,"epsEstimate":-0.04,"surprisePct":-25.0}]}