{"fundamentals":{"marketCapB":8.899,"targetPrice":387.5,"avgVolume":92561.0,"volume":547789.0,"prevClose":333.72,"week52High":346.2,"week52Low":174.92,"exchange":"NYSE","salesB":1.095,"grossProfitB":0.461,"operIncomeB":0.173,"incomeB":0.299,"cashB":0.101,"assetsB":2.41,"liabilitiesB":0.87,"equityB":1.541,"debtB":0.186,"currentRatio":135.49,"quickRatio":92.63,"grossMargin":42.09,"operMargin":15.81,"profitMargin":27.32,"roe":19.42,"epsTtm":7.47,"epsNextY":8.44,"epsNextQ":2.09,"sharesB":0.026,"pe":45.98,"forwardPE":40.7,"ps":8.13,"pb":5.77,"debtEq":0.12,"source":"nasdaq"},"news":[{"title":"JPMorgan Initiates ESCO Technologies at Overweight With $420 Price Target","publisher":"MT Newswires","link":"https://finance.yahoo.com/markets/stocks/articles/jpmorgan-initiates-esco-technologies-overweight-095728609.html","publishedAt":"2026-06-15"},{"title":"ESCO Technologies Megger Deal Reshapes Testing Focus And Balance Sheet Profile","publisher":"Simply Wall St.","link":"https://finance.yahoo.com/markets/stocks/articles/esco-technologies-megger-deal-reshapes-170902660.html","publishedAt":"2026-06-14"},{"title":"3 Reasons Investors Love ESCO (ESE)","publisher":"StockStory","link":"https://finance.yahoo.com/markets/stocks/articles/3-reasons-investors-love-esco-170150126.html","publishedAt":"2026-06-09"},{"title":"2 High-Flying Stocks on Our Buy List and 1 We Find Risky","publisher":"StockStory","link":"https://finance.yahoo.com/markets/stocks/articles/2-high-flying-stocks-buy-154950448.html","publishedAt":"2026-06-09"},{"title":"1 Small-Cap Stock with Exciting Potential and 2 We Ignore","publisher":"StockStory","link":"https://finance.yahoo.com/markets/stocks/articles/1-small-cap-stock-exciting-151827456.html","publishedAt":"2026-05-29"},{"title":"1 of Wall Street’s Favorite Stock for Long-Term Investors and 2 We Avoid","publisher":"StockStory","link":"https://finance.yahoo.com/markets/stocks/articles/1-wall-street-favorite-stock-091551163.html","publishedAt":"2026-05-25"},{"title":"How ESCO Technologies' (ESE) Revenue Miss Amid Strong Orders Has Changed Its Investment Story","publisher":"Simply Wall St.","link":"https://finance.yahoo.com/markets/stocks/articles/esco-technologies-ese-revenue-miss-001442617.html","publishedAt":"2026-05-24"},{"title":"2 Growth Stocks Set to Flourish and 1 Facing Challenges","publisher":"StockStory","link":"https://finance.yahoo.com/markets/stocks/articles/2-growth-stocks-set-flourishand-134055177.html","publishedAt":"2026-05-23"}],"ticker":"ESE","company":"ESCO Technologies Inc.","historySource":"snapshot","earningsHistory":[{"date":"2023-08-08","epsActual":1.09,"epsEstimate":1.0,"surprisePct":9.36},{"date":"2023-11-16","epsActual":1.25,"epsEstimate":1.22,"surprisePct":2.46},{"date":"2024-02-08","epsActual":0.62,"epsEstimate":0.65,"surprisePct":-5.1},{"date":"2024-05-10","epsActual":0.94,"epsEstimate":0.87,"surprisePct":8.46},{"date":"2024-08-07","epsActual":1.16,"epsEstimate":1.2,"surprisePct":-3.6},{"date":"2024-11-14","epsActual":1.46,"epsEstimate":1.44,"surprisePct":1.74},{"date":"2025-02-06","epsActual":1.07,"epsEstimate":0.73,"surprisePct":47.08},{"date":"2025-05-07","epsActual":1.35,"epsEstimate":1.25,"surprisePct":8.29},{"date":"2025-08-07","epsActual":1.6,"epsEstimate":1.65,"surprisePct":-2.83},{"date":"2025-11-20","epsActual":2.32,"epsEstimate":2.13,"surprisePct":8.67},{"date":"2026-02-05","epsActual":1.64,"epsEstimate":1.32,"surprisePct":24.24},{"date":"2026-05-07","epsActual":1.91,"epsEstimate":1.84,"surprisePct":3.8}]}