{"fundamentals":{"marketCapB":0.221,"targetPrice":10.08,"avgVolume":3303391.0,"volume":190800.454782,"prevClose":6.21,"week52High":9.7401,"week52Low":3.09,"exchange":"AMEX","salesB":0.597,"grossProfitB":0.331,"operIncomeB":-0.147,"incomeB":-0.193,"cashB":0.083,"assetsB":1.586,"liabilitiesB":1.357,"equityB":0.229,"debtB":0.708,"currentRatio":60.03,"quickRatio":44.46,"grossMargin":55.46,"operMargin":-24.64,"profitMargin":-32.36,"roe":-84.43,"sharesB":0.035,"ps":0.37,"pb":0.97,"debtEq":3.09,"source":"nasdaq"},"news":[{"title":"Sector Update: Energy Stocks Decline Premarket Wednesday","publisher":"MT Newswires","link":"https://finance.yahoo.com/sectors/energy/articles/sector-energy-stocks-decline-premarket-132432126.html","publishedAt":"2026-05-27"},{"title":"Gran Tierra Energy Up 2.35% In US Premarket As Satisfies Conditions Precedent for Tisquirama Contract","publisher":"MT Newswires","link":"https://finance.yahoo.com/sectors/energy/articles/gran-tierra-energy-2-35-105644187.html","publishedAt":"2026-05-27"},{"title":"Gran Tierra Secures 49% Stake in Colombia's Tisquirama Block From Ecopetrol","publisher":"MT Newswires","link":"https://finance.yahoo.com/sectors/energy/articles/gran-tierra-secures-49-stake-105324164.html","publishedAt":"2026-05-27"},{"title":"EnerCom Announces Premier Networking Events for the 31st Annual Energy Investment Conference, Including Monday Charity Golf Tournament, Monday VIP Welcome Mixer, and Tuesday Casino Night","publisher":"PR Newswire","link":"https://finance.yahoo.com/sectors/energy/articles/enercom-announces-premier-networking-events-180000007.html","publishedAt":"2026-05-22"},{"title":"Should You Add Canadian Natural Stock to Your Portfolio Now?","publisher":"Zacks","link":"https://finance.yahoo.com/markets/stocks/articles/add-canadian-natural-stock-portfolio-150300303.html","publishedAt":"2026-05-19"},{"title":"Gran Tierra Energy Announces Final Voting Results of its Annual Meeting of Stockholders","publisher":"GlobeNewswire","link":"https://finance.yahoo.com/markets/stocks/articles/gran-tierra-energy-announces-final-221900896.html","publishedAt":"2026-05-09"},{"title":"Gran Tierra Energy Inc. Q1 2026 Earnings Call Summary","publisher":"Moby","link":"https://finance.yahoo.com/m/62dd9ad9-36ce-30ac-b84d-ba7d972c23a7/gran-tierra-energy-inc.-q1.html","publishedAt":"2026-05-08"},{"title":"Gran Tierra Energy Reports Wider Q1 Net Loss; Revises 2026 Guidance","publisher":"MT Newswires","link":"https://finance.yahoo.com/sectors/energy/articles/gran-tierra-energy-reports-wider-115834391.html","publishedAt":"2026-05-08"}],"ticker":"GTE","company":"Gran Tierra Energy Inc.","historySource":"snapshot","earningsHistory":[{"date":"2022-11-01","epsActual":1.0,"epsEstimate":1.25,"surprisePct":-20.0},{"date":"2023-02-21","epsActual":0.9,"epsEstimate":0.4,"surprisePct":125.0},{"date":"2023-08-01","epsActual":-0.33,"epsEstimate":-0.6,"surprisePct":45.0},{"date":"2023-10-31","epsActual":0.2,"epsEstimate":-0.45,"surprisePct":144.44},{"date":"2024-02-20","epsActual":0.23,"epsEstimate":-0.13,"surprisePct":276.92},{"date":"2024-07-31","epsActual":1.16,"epsEstimate":0.23,"surprisePct":404.35},{"date":"2024-11-04","epsActual":0.04,"epsEstimate":0.14,"surprisePct":-71.43},{"date":"2025-02-24","epsActual":-0.85,"epsEstimate":0.03,"surprisePct":-2928.33},{"date":"2025-05-02","epsActual":-0.54,"epsEstimate":-0.23,"surprisePct":-134.78},{"date":"2025-07-30","epsActual":-0.36,"epsEstimate":-0.43,"surprisePct":16.28},{"date":"2026-03-03","epsActual":-4.0,"epsEstimate":-0.16,"surprisePct":-2400.0},{"date":"2026-05-07","epsActual":-3.38,"epsEstimate":-1.32,"surprisePct":-156.06}]}