{"fundamentals":{"sharesB":0.016,"source":"nasdaq"},"news":[{"title":"FBG Bid Co. Acquires FAT Brands Assets for $595 Million","publisher":"GlobeNewswire","link":"https://finance.yahoo.com/markets/stocks/articles/fbg-bid-co-acquires-fat-142000728.html","publishedAt":"2026-06-16"},{"title":"Huron Consulting (HURN) Posts Record Revenue and Fully Reaffirms Its Outlook for the Year","publisher":"Insider Monkey","link":"https://finance.yahoo.com/markets/stocks/articles/huron-consulting-hurn-posts-record-214320549.html","publishedAt":"2026-06-05"},{"title":"Huron Adds RelateCare To Deepen AI Led Healthcare Managed Services","publisher":"Simply Wall St.","link":"https://finance.yahoo.com/sectors/healthcare/articles/huron-adds-relatecare-deepen-ai-091024195.html","publishedAt":"2026-06-04"},{"title":"Huron Consulting Acquires RelateCare for Undisclosed Sum","publisher":"MT Newswires","link":"https://finance.yahoo.com/sectors/healthcare/articles/huron-consulting-acquires-relatecare-undisclosed-140257424.html","publishedAt":"2026-06-03"},{"title":"Huron Acquires RelateCare to Strengthen Patient Access and Care Coordination Capabilities","publisher":"Business Wire","link":"https://finance.yahoo.com/sectors/healthcare/articles/huron-acquires-relatecare-strengthen-patient-133900727.html","publishedAt":"2026-06-03"},{"title":"Q1 Earnings Outperformers: Huron (NASDAQ:HURN) And The Rest Of The Business Process Outsourcing & Consulting Stocks","publisher":"StockStory","link":"https://finance.yahoo.com/markets/stocks/articles/q1-earnings-outperformers-huron-nasdaq-195324891.html","publishedAt":"2026-05-28"},{"title":"2 of Wall Street’s Favorite Stocks with Exciting Potential and 1 We Brush Off","publisher":"StockStory","link":"https://finance.yahoo.com/markets/stocks/articles/2-wall-street-favorite-stocks-102751672.html","publishedAt":"2026-05-25"},{"title":"2 Services Stocks to Consider Right Now and 1 We Turn Down","publisher":"StockStory","link":"https://finance.yahoo.com/markets/stocks/articles/2-services-stocks-consider-now-190055999.html","publishedAt":"2026-05-22"}],"ticker":"HURN","company":"Huron Consulting Group Inc.","historySource":"snapshot"}