{"fundamentals":{"marketCapB":0.11,"avgVolume":13365.0,"volume":8154.0,"prevClose":6.0,"week52High":16.4,"week52Low":3.5,"exchange":"NCM","epsTtm":-0.4,"salesB":0.459,"grossProfitB":0.124,"incomeB":-0.053,"cashB":0.159,"debtB":0.211,"profitMargin":-11.44,"grossMargin":27.02,"operMargin":-4.57,"roe":-138.29,"currentRatio":1.55,"quickRatio":1.33,"sharesB":0.017,"ps":0.24,"source":"nasdaq+yahoo"},"news":[{"title":"MASTERBEEF GROUP Announces Planned Launch of Premium Thai Tea Beverage and Dessert Franchise in Hong Kong and Macau","publisher":"GlobeNewswire","link":"https://finance.yahoo.com/markets/stocks/articles/masterbeef-group-announces-planned-launch-130000494.html","publishedAt":"2026-05-12"},{"title":"Assessing Mediobanca (BIT:MB) Valuation After Strong Recent Share Price Momentum","publisher":"Simply Wall St.","link":"https://finance.yahoo.com/markets/stocks/articles/assessing-mediobanca-bit-mb-valuation-190557768.html","publishedAt":"2026-04-18"},{"title":"Ousted Monte Paschi Boss Says CEO Change Raises Mediobanca Integration Risk","publisher":"The Wall Street Journal","link":"https://finance.yahoo.com/m/9506bced-bd34-30a4-9f15-49676686a3c2/ousted-monte-paschi-boss-says.html","publishedAt":"2026-04-03"}],"ticker":"MB","company":"MasterBeef Group Ordinary Shares","historySource":"snapshot"}