{"fundamentals":{"marketCapB":10.176,"targetPrice":600.0,"avgVolume":317978.0,"volume":702576.506661,"prevClose":571.87,"week52High":636.045,"week52Low":345.2301,"exchange":"NYSE","salesB":19.384,"grossProfitB":2.359,"operIncomeB":0.719,"incomeB":0.471,"cashB":0.029,"assetsB":4.726,"liabilitiesB":4.102,"equityB":0.624,"debtB":2.183,"currentRatio":80.49,"quickRatio":36.03,"grossMargin":12.17,"operMargin":3.71,"profitMargin":2.43,"roe":75.48,"epsTtm":29.42,"epsNextY":29.28,"epsNextQ":9.48,"sharesB":0.018,"pe":18.74,"forwardPE":18.83,"ps":0.52,"pb":16.31,"debtEq":3.5,"source":"nasdaq"},"news":[{"title":"4 Stocks Trading Near 52-Week High With Room to Rise Further","publisher":"Zacks","link":"https://finance.yahoo.com/markets/stocks/articles/4-stocks-trading-near-52-152800348.html","publishedAt":"2026-06-19"},{"title":"New Strong Buy Stocks for June 18th","publisher":"Zacks","link":"https://finance.yahoo.com/markets/stocks/articles/strong-buy-stocks-june-18th-090500842.html","publishedAt":"2026-06-18"},{"title":"Best Value Stocks to Buy for June 18th","publisher":"Zacks","link":"https://finance.yahoo.com/markets/stocks/articles/best-value-stocks-buy-june-075100201.html","publishedAt":"2026-06-18"},{"title":"Is Casey's General Stores (CASY) Outperforming Other Retail-Wholesale Stocks This Year?","publisher":"Zacks","link":"https://finance.yahoo.com/markets/stocks/articles/caseys-general-stores-casy-outperforming-134003224.html","publishedAt":"2026-06-17"},{"title":"MUSA vs. CASY: Which Convenience Store Stock Is the Better Buy Now?","publisher":"Zacks","link":"https://finance.yahoo.com/markets/stocks/articles/musa-vs-casy-convenience-store-125400309.html","publishedAt":"2026-06-17"},{"title":"Petrobras Signs R$443.7M Decommissioning Contract With OceanPact","publisher":"Zacks","link":"https://finance.yahoo.com/energy/articles/petrobras-signs-r-443-7m-142300628.html","publishedAt":"2026-06-16"},{"title":"Chevron Secures Strategic Entry Into Greece's Offshore Block 10","publisher":"Zacks","link":"https://finance.yahoo.com/energy/articles/chevron-secures-strategic-entry-greeces-141900418.html","publishedAt":"2026-06-16"},{"title":"The Zacks Analyst Blog Highlights Albemarle, Dycom Industries and Murphy USA","publisher":"Zacks","link":"https://finance.yahoo.com/markets/stocks/articles/zacks-analyst-blog-highlights-albemarle-082900965.html","publishedAt":"2026-06-16"}],"ticker":"MUSA","company":"Murphy USA Inc.","historySource":"snapshot","earningsHistory":[{"date":"2023-08-02","epsActual":6.02,"epsEstimate":6.28,"surprisePct":-4.11},{"date":"2023-11-01","epsActual":7.69,"epsEstimate":6.55,"surprisePct":17.46},{"date":"2024-02-07","epsActual":7.0,"epsEstimate":6.65,"surprisePct":5.28},{"date":"2024-05-01","epsActual":3.12,"epsEstimate":4.46,"surprisePct":-30.04},{"date":"2024-07-31","epsActual":6.92,"epsEstimate":7.05,"surprisePct":-1.82},{"date":"2024-10-30","epsActual":7.2,"epsEstimate":7.07,"surprisePct":1.8},{"date":"2025-02-05","epsActual":7.5,"epsEstimate":6.68,"surprisePct":12.27},{"date":"2025-05-07","epsActual":2.63,"epsEstimate":3.74,"surprisePct":-29.74},{"date":"2025-07-30","epsActual":7.36,"epsEstimate":6.56,"surprisePct":12.12},{"date":"2025-10-29","epsActual":6.76,"epsEstimate":6.95,"surprisePct":-2.76},{"date":"2026-02-04","epsActual":7.88,"epsEstimate":6.9,"surprisePct":14.19},{"date":"2026-04-29","epsActual":7.28,"epsEstimate":5.5,"surprisePct":32.28}]}