{"fundamentals":{"sharesB":0.015,"source":"nasdaq"},"news":[{"title":"Net Lease Office Properties Announces Postponement of Annual Meeting of Shareholders","publisher":"PR Newswire","link":"https://finance.yahoo.com/markets/stocks/articles/net-lease-office-properties-announces-200500469.html","publishedAt":"2026-06-13"},{"title":"Should You Hold Net Lease Office Properties (NLOP)?","publisher":"Insider Monkey","link":"https://finance.yahoo.com/markets/stocks/articles/hold-net-lease-office-properties-143054696.html","publishedAt":"2026-04-08"}],"ticker":"NLOP","company":"Net Lease Office Properties Common Shares of Beneficial Interest","historySource":"snapshot"}