{"fundamentals":{"marketCapB":2.127,"targetPrice":58.0,"avgVolume":175933.0,"volume":259619.746475,"prevClose":50.53,"week52High":55.99,"week52Low":39.2915,"exchange":"NYSE","salesB":1.289,"grossProfitB":0.518,"operIncomeB":0.281,"incomeB":0.113,"cashB":0.037,"assetsB":6.167,"liabilitiesB":4.692,"equityB":1.475,"debtB":2.668,"currentRatio":72.08,"quickRatio":56.82,"grossMargin":40.19,"operMargin":21.79,"profitMargin":8.79,"roe":7.68,"epsTtm":3.0,"epsNextY":0.73,"epsNextQ":0.03,"sharesB":0.042,"pe":16.83,"forwardPE":69.18,"ps":1.65,"pb":1.44,"debtEq":1.81,"source":"nasdaq"},"news":[{"title":"NWN: What does Argus have to say about NWN?","publisher":"Argus Research","link":"https://finance.yahoo.com/m/b99da26f-b85b-34d0-bc31-20aac0a7e95b/nwn%3A-what-does-argus-have-to.html","publishedAt":"2026-06-24"},{"title":"OGS vs. NWN: Which Gas Utility Stock Is a Better Investment Pick?","publisher":"Zacks","link":"https://finance.yahoo.com/markets/stocks/articles/ogs-vs-nwn-gas-utility-175400508.html","publishedAt":"2026-06-02"},{"title":"Northwest Natural Gas Q1 Earnings Call Highlights","publisher":"MarketBeat","link":"https://finance.yahoo.com/m/c900e91d-d577-36ae-a273-f3377073e5f9/northwest-natural-gas-q1.html","publishedAt":"2026-05-13"},{"title":"Does Northwest Natural (NWN) Insider Buying Reinforce Confidence in Its Earnings Durability Narrative?","publisher":"Simply Wall St.","link":"https://finance.yahoo.com/markets/stocks/articles/does-northwest-natural-nwn-insider-060635958.html","publishedAt":"2026-05-10"},{"title":"UGI Q2 Earnings & Revenues Lag Estimates, Sales Increase Y/Y","publisher":"Zacks","link":"https://finance.yahoo.com/markets/stocks/articles/ugi-q2-earnings-revenues-lag-162000729.html","publishedAt":"2026-05-09"},{"title":"MDU Resources Q1 Earnings Miss Estimates, Revenues Decline Y/Y","publisher":"Zacks","link":"https://finance.yahoo.com/markets/stocks/articles/mdu-resources-q1-earnings-miss-154800658.html","publishedAt":"2026-05-09"},{"title":"Northwest Natural Holding Company Q1 2026 Earnings Call Summary","publisher":"Moby","link":"https://finance.yahoo.com/m/5414ec84-df86-335d-b06c-56ee5d593f5d/northwest-natural-holding.html","publishedAt":"2026-05-07"},{"title":"NW Natural (NWN) misses first-quarter expectations but maintains full-year outlook","publisher":"InvestorsHub","link":"https://finance.yahoo.com/m/34be7957-1e60-3690-aee3-00147e02841f/nw-natural-%28nwn%29-misses.html","publishedAt":"2026-05-06"}],"ticker":"NWN","company":"Northwest Natural Holding Company","historySource":"snapshot","earningsHistory":[{"date":"2023-08-03","epsActual":0.03,"epsEstimate":-0.01,"surprisePct":450.06},{"date":"2023-11-03","epsActual":-0.65,"epsEstimate":-0.67,"surprisePct":3.4},{"date":"2024-02-23","epsActual":1.21,"epsEstimate":1.28,"surprisePct":-5.22},{"date":"2024-05-06","epsActual":1.69,"epsEstimate":1.81,"surprisePct":-6.63},{"date":"2024-08-02","epsActual":-0.07,"epsEstimate":-0.13,"surprisePct":45.45},{"date":"2024-11-12","epsActual":-0.71,"epsEstimate":-0.8,"surprisePct":11.25},{"date":"2025-02-28","epsActual":1.41,"epsEstimate":1.41,"surprisePct":-0.28},{"date":"2025-05-06","epsActual":2.28,"epsEstimate":2.01,"surprisePct":13.43},{"date":"2025-08-05","epsActual":0.01,"epsEstimate":-0.13,"surprisePct":107.81},{"date":"2025-11-05","epsActual":-0.73,"epsEstimate":-0.83,"surprisePct":11.62},{"date":"2026-02-27","epsActual":1.39,"epsEstimate":1.36,"surprisePct":2.21},{"date":"2026-05-06","epsActual":2.33,"epsEstimate":2.4,"surprisePct":-3.02}]}