{"fundamentals":{"marketCapB":0.012,"avgVolume":215373.0,"volume":33075.0,"prevClose":0.473,"week52High":1.908,"week52Low":0.4509,"exchange":"NASDAQ-CM","salesB":0.01,"grossProfitB":0.003,"operIncomeB":-0.007,"incomeB":-0.007,"cashB":0.004,"assetsB":0.007,"liabilitiesB":0.003,"equityB":0.004,"debtB":0,"currentRatio":125.44,"quickRatio":125.44,"grossMargin":31.93,"operMargin":-75.75,"profitMargin":-75.17,"roe":-191.62,"sharesB":0.024,"ps":1.2,"pb":3.0,"debtEq":0.0,"source":"nasdaq"},"news":[{"title":"Top Premarket Decliners","publisher":"MT Newswires","link":"https://finance.yahoo.com/markets/stocks/articles/top-premarket-decliners-113427850.html","publishedAt":"2026-06-08"},{"title":"Is Ohmyhome (NASDAQ:OMH) In A Good Position To Deliver On Growth Plans?","publisher":"Simply Wall St.","link":"https://finance.yahoo.com/markets/stocks/articles/ohmyhome-nasdaq-omh-good-position-105431927.html","publishedAt":"2026-05-06"}],"ticker":"OMH","company":"Ohmyhome Limited Class A Ordinary Shares","historySource":"snapshot"}