{"fundamentals":{"marketCapB":4.702,"targetPrice":24.0,"volume":1291920.0,"prevClose":23.53,"week52High":26.15,"week52Low":16.685,"exchange":"NASDAQ-GS","salesB":44.262,"grossProfitB":2.675,"operIncomeB":1.428,"incomeB":0.26,"cashB":0.329,"assetsB":31.276,"liabilitiesB":17.06,"debtB":11.259,"currentRatio":95.96,"quickRatio":91.66,"grossMargin":6.04,"operMargin":3.23,"profitMargin":0.59,"epsTtm":0.77,"epsNextY":1.61,"epsNextQ":0.47,"sharesB":0.22,"pe":27.82,"forwardPE":13.31,"ps":0.11,"source":"nasdaq"},"news":[{"title":"Plains All American Pipeline and Plains GP Holdings Provide Updated Capital Spending Guidance for 2026","publisher":"GlobeNewswire","link":"https://finance.yahoo.com/sectors/energy/articles/plains-american-pipeline-plains-gp-113000672.html","publishedAt":"2026-06-15"},{"title":"Goldman Sachs Upgrades Plains GP to Neutral From Sell, Adjusts Price Target to $24 From $18","publisher":"MT Newswires","link":"https://finance.yahoo.com/markets/stocks/articles/goldman-sachs-upgrades-plains-gp-111810801.html","publishedAt":"2026-06-04"},{"title":"Why This $3 Million Plains GP Holdings Buy Could Signal Confidence in a $2.9 Billion Outlook","publisher":"Motley Fool","link":"https://finance.yahoo.com/m/3e90c96b-62ae-339f-bab3-4050d418b4a2/why-this-%243-million-plains-gp.html","publishedAt":"2026-06-01"},{"title":"Should Value Investors Buy Plains Group (PAGP) Stock?","publisher":"Zacks","link":"https://finance.yahoo.com/markets/stocks/articles/value-investors-buy-plains-group-134002174.html","publishedAt":"2026-05-19"},{"title":"Plains All American Pipeline and Plains GP Holdings Announce Completion of Canadian NGL Divestiture","publisher":"GlobeNewswire","link":"https://finance.yahoo.com/sectors/energy/articles/plains-american-pipeline-plains-gp-142900744.html","publishedAt":"2026-05-12"},{"title":"The Bull Case For Plains GP Holdings (PAGP) Could Change Following Raised EBITDA Outlook And NGL Exit Moves","publisher":"Simply Wall St.","link":"https://finance.yahoo.com/markets/stocks/articles/bull-case-plains-gp-holdings-111659564.html","publishedAt":"2026-05-12"},{"title":"Plains All American Pipeline, L.P. and Plains GP Holdings Announce Appointment of New Board Member","publisher":"GlobeNewswire","link":"https://finance.yahoo.com/sectors/energy/articles/plains-american-pipeline-l-p-201500219.html","publishedAt":"2026-05-12"},{"title":"Plains GP Holdings, L.P. Q1 2026 Earnings Call Summary","publisher":"Moby","link":"https://finance.yahoo.com/m/9296b4dc-6f09-3fb0-8f0d-fee09bf1cbd4/plains-gp-holdings%2C-l.p.-q1.html","publishedAt":"2026-05-09"}],"ticker":"PAGP","company":"Plains GP Holdings, L.P. - Class A Shares representing limited partner interests","historySource":"snapshot","earningsHistory":[{"date":"2023-08-04","epsActual":0.25,"epsEstimate":0.25,"surprisePct":-0.49},{"date":"2023-11-03","epsActual":0.35,"epsEstimate":0.32,"surprisePct":9.38},{"date":"2024-02-09","epsActual":0.42,"epsEstimate":0.46,"surprisePct":-9.06},{"date":"2024-05-03","epsActual":0.41,"epsEstimate":0.39,"surprisePct":5.13},{"date":"2024-08-02","epsActual":0.31,"epsEstimate":0.4,"surprisePct":-22.5},{"date":"2024-11-08","epsActual":0.37,"epsEstimate":0.37,"surprisePct":1.37},{"date":"2025-02-07","epsActual":0.46,"epsEstimate":0.48,"surprisePct":-3.25},{"date":"2025-05-09","epsActual":0.23,"epsEstimate":0.48,"surprisePct":-51.94},{"date":"2025-08-08","epsActual":0.41,"epsEstimate":0.52,"surprisePct":-21.2},{"date":"2025-11-05","epsActual":0.83,"epsEstimate":0.4,"surprisePct":107.41},{"date":"2026-02-06","epsActual":0.36,"epsEstimate":0.46,"surprisePct":-21.69},{"date":"2026-05-08","epsActual":1.12,"epsEstimate":0.67,"surprisePct":65.77}]}