{"fundamentals":{"sharesB":0.019,"source":"nasdaq"},"news":[{"title":"RH is Chasing Luxury Growth as Tariffs Reshape the Playbook","publisher":"Zacks","link":"https://finance.yahoo.com/real-estate/articles/rh-chasing-luxury-growth-tariffs-172000967.html","publishedAt":"2026-06-17"},{"title":"Is RH Stock a Buy Now or a Value Trap for Patient Investors?","publisher":"Zacks","link":"https://finance.yahoo.com/markets/stocks/articles/rh-stock-buy-now-value-171700825.html","publishedAt":"2026-06-17"},{"title":"RH Stock Outlook Hinges on Tariffs, Housing and a Big Reset","publisher":"Zacks","link":"https://finance.yahoo.com/markets/stocks/articles/rh-stock-outlook-hinges-tariffs-171400858.html","publishedAt":"2026-06-17"},{"title":"Do Options Traders Know Something About RH Stock We Don't?","publisher":"Zacks","link":"https://finance.yahoo.com/markets/options/articles/options-traders-know-something-rh-124000959.html","publishedAt":"2026-06-16"},{"title":"June 2026's Leading Growth Stocks With Strong Insider Ownership","publisher":"Simply Wall St.","link":"https://finance.yahoo.com/markets/stocks/articles/june-2026s-leading-growth-stocks-173645951.html","publishedAt":"2026-06-16"},{"title":"RH’s Strong Q1 Still Leaves Investors With One Big Question","publisher":"MarketBeat","link":"https://finance.yahoo.com/m/feb7ecfc-ee44-302c-b903-3c1d3c18f3d0/rh%E2%80%99s-strong-q1-still-leaves.html","publishedAt":"2026-06-16"},{"title":"Analyst Report: RH","publisher":"Morningstar Research","link":"https://finance.yahoo.com/m/0c941e29-ffdc-3697-a4a2-d9e4fd26ce78/analyst-report%3A-rh.html","publishedAt":"2026-06-16"},{"title":"Down 75% in 5 Years, Is RH Stock Finally Positioned for a Turnaround?","publisher":"Motley Fool","link":"https://finance.yahoo.com/m/c0908aaf-19ad-30c1-857f-49ad2ed3c391/down-75%25-in-5-years%2C-is-rh.html","publishedAt":"2026-06-15"}],"ticker":"RH","company":"RH","historySource":"snapshot"}