{"fundamentals":{"marketCapB":0.129,"targetPrice":2.5,"avgVolume":1262941.0,"volume":217408.0,"prevClose":8.85,"week52High":20.0,"week52Low":2.23,"exchange":"NYQ","epsTtm":-4.15,"epsNextY":-3.33,"salesB":0.112,"grossProfitB":0.098,"incomeB":-0.064,"cashB":0.185,"debtB":0.129,"profitMargin":-57.48,"grossMargin":87.75,"operMargin":-55.83,"roe":-49.58,"currentRatio":1.13,"quickRatio":1.09,"forwardPE":-2.49,"sharesB":0.016,"ps":1.15,"source":"nasdaq+yahoo"},"news":[{"title":"Skillz Plans to Change Corporate Name to Firy","publisher":"MT Newswires","link":"https://finance.yahoo.com/markets/stocks/articles/skillz-plans-change-corporate-name-140144741.html","publishedAt":"2026-06-08"},{"title":"The pitch trick that helped an esports startup raise $20M when VCs only wanted AI","publisher":"TechCrunch","link":"https://finance.yahoo.com/markets/stocks/articles/pitch-trick-helped-esports-startup-150000786.html","publishedAt":"2026-05-26"},{"title":"Skillz Inc (SKLZ) Q1 2026 Earnings Call Highlights: Revenue Growth and Strategic Shifts Amid ...","publisher":"GuruFocus.com","link":"https://finance.yahoo.com/markets/stocks/articles/skillz-inc-sklz-q1-2026-050045944.html","publishedAt":"2026-05-20"},{"title":"Skillz (SKLZ) Q1 2026 Earnings Transcript","publisher":"Motley Fool","link":"https://finance.yahoo.com/m/a87b3a23-5427-3d2c-91f5-414a868c829b/skillz-%28sklz%29-q1-2026.html","publishedAt":"2026-05-20"},{"title":"Skillz (SKLZ) Q4 2025 Earnings Transcript","publisher":"Motley Fool","link":"https://finance.yahoo.com/m/290a96f9-066a-3a64-a445-f11bafee1b23/skillz-%28sklz%29-q4-2025.html","publishedAt":"2026-05-20"},{"title":"Skillz Q1 Earnings Call Highlights","publisher":"MarketBeat","link":"https://finance.yahoo.com/m/a755276f-55de-3977-a7c4-314f09dbaf5b/skillz-q1-earnings-call.html","publishedAt":"2026-05-20"},{"title":"Skillz Q1 Loss Narrows, Revenue Increases","publisher":"MT Newswires","link":"https://finance.yahoo.com/markets/stocks/articles/skillz-q1-loss-narrows-revenue-202112678.html","publishedAt":"2026-05-16"},{"title":"Skillz Reports First Quarter 2026 Results","publisher":"Business Wire","link":"https://finance.yahoo.com/markets/stocks/articles/skillz-reports-first-quarter-2026-200500459.html","publishedAt":"2026-05-16"}],"ticker":"SKLZ","company":"Skillz Inc. Class A","historySource":"snapshot"}