{"fundamentals":{"marketCapB":4.722,"targetPrice":234.5,"avgVolume":1322249.0,"volume":875507.347947,"prevClose":165.47,"week52High":381.45,"week52Low":116.35,"exchange":"NASDAQ-GS","salesB":0.697,"grossProfitB":0.601,"operIncomeB":0.179,"incomeB":0.174,"cashB":0.223,"assetsB":0.693,"liabilitiesB":1.43,"equityB":-0.737,"debtB":1.209,"currentRatio":326.34,"quickRatio":326.34,"grossMargin":86.22,"operMargin":25.73,"profitMargin":25.01,"roe":-23.65,"epsTtm":4.27,"epsNextY":4.66,"epsNextQ":1.02,"sharesB":0.027,"pe":40.61,"forwardPE":37.21,"ps":6.77,"debtEq":-1.64,"source":"nasdaq"},"news":[{"title":"Wingstop Inc. to Announce Fiscal Second Quarter 2026 Financial Results on July 29, 2026","publisher":"PR Newswire","link":"https://finance.yahoo.com/markets/stocks/articles/wingstop-inc-announce-fiscal-second-120000977.html","publishedAt":"2026-06-30"},{"title":"Wingstop (WING) Stock After 51% Slide In A Year Is The Valuation Now Sensible","publisher":"Simply Wall St.","link":"https://finance.yahoo.com/markets/stocks/articles/wingstop-wing-stock-51-slide-001530481.html","publishedAt":"2026-06-26"},{"title":"Is Wingstop's Sweet Heat Chamoy Push Signaling a Deeper Shift in Digital Engagement Strategy (WING)?","publisher":"Simply Wall St.","link":"https://finance.yahoo.com/markets/stocks/articles/wingstops-sweet-heat-chamoy-push-160856413.html","publishedAt":"2026-06-26"},{"title":"Wingstop Elevates its Summer Flavor Game with New Sweet Heat Chamoy Featuring Tajín","publisher":"PR Newswire","link":"https://finance.yahoo.com/media-advertising/articles/wingstop-elevates-summer-flavor-game-113000121.html","publishedAt":"2026-06-25"},{"title":"El Pollo Loco and Wingstop Stocks Trade Up, What You Need To Know","publisher":"StockStory","link":"https://finance.yahoo.com/markets/stocks/articles/el-pollo-loco-wingstop-stocks-020025484.html","publishedAt":"2026-06-25"},{"title":"BofA Securities Cuts Wingstop Price Target to $234 From $264","publisher":"MT Newswires","link":"https://finance.yahoo.com/markets/stocks/articles/bofa-securities-cuts-wingstop-price-121739139.html","publishedAt":"2026-06-24"},{"title":"RBC Cuts Price Target on Wingstop to $225 From $250, Keeps Outperform Rating","publisher":"MT Newswires","link":"https://finance.yahoo.com/markets/stocks/articles/rbc-cuts-price-target-wingstop-110921633.html","publishedAt":"2026-06-23"},{"title":"Wingstop (WING) Falls More Steeply Than Broader Market: What Investors Need to Know","publisher":"Zacks","link":"https://finance.yahoo.com/markets/stocks/articles/wingstop-wing-falls-more-steeply-221504429.html","publishedAt":"2026-06-23"}],"ticker":"WING","company":"Wingstop Inc.","historySource":"snapshot","earningsHistory":[{"date":"2023-08-02","epsActual":0.57,"epsEstimate":0.51,"surprisePct":11.13},{"date":"2023-11-01","epsActual":0.69,"epsEstimate":0.52,"surprisePct":33.19},{"date":"2024-02-21","epsActual":0.64,"epsEstimate":0.57,"surprisePct":12.11},{"date":"2024-05-01","epsActual":0.98,"epsEstimate":0.77,"surprisePct":28.1},{"date":"2024-07-31","epsActual":0.93,"epsEstimate":0.83,"surprisePct":12.01},{"date":"2024-10-30","epsActual":0.89,"epsEstimate":0.96,"surprisePct":-6.58},{"date":"2025-02-19","epsActual":0.95,"epsEstimate":0.87,"surprisePct":9.64},{"date":"2025-04-30","epsActual":1.03,"epsEstimate":0.87,"surprisePct":18.5},{"date":"2025-07-30","epsActual":1.0,"epsEstimate":0.87,"surprisePct":15.0},{"date":"2025-11-04","epsActual":1.09,"epsEstimate":0.92,"surprisePct":19.04},{"date":"2026-02-18","epsActual":1.0,"epsEstimate":0.83,"surprisePct":19.98},{"date":"2026-04-29","epsActual":1.18,"epsEstimate":1.03,"surprisePct":15.09}]}