{"fundamentals":{"marketCapB":10.918,"targetPrice":176.0,"avgVolume":452469.0,"volume":622282.843026,"prevClose":159.81,"week52High":162.96,"week52Low":119.61,"exchange":"NASDAQ-GS","salesB":4.23,"incomeB":0.824,"cashB":13.584,"assetsB":71.142,"liabilitiesB":63.883,"equityB":7.259,"debtB":3.929,"currentRatio":NaN,"quickRatio":NaN,"grossMargin":0.0,"operMargin":0.0,"profitMargin":19.48,"roe":11.35,"epsTtm":12.21,"epsNextY":12.98,"epsNextQ":3.15,"sharesB":0.067,"pe":13.26,"forwardPE":12.47,"ps":2.58,"pb":1.5,"debtEq":0.54,"source":"nasdaq"},"news":[{"title":"WTFC: Raising target price to $175.00","publisher":"Argus Research","link":"https://finance.yahoo.com/m/4f870207-2c18-3911-8dd5-7d3c13d9f605/wtfc%3A-raising-target-price-to.html","publishedAt":"2026-06-24"},{"title":"Q1 Earnings Highs And Lows: Wintrust Financial (NASDAQ:WTFC) Vs The Rest Of The Regional Banks Stocks","publisher":"StockStory","link":"https://finance.yahoo.com/markets/stocks/articles/q1-earnings-highs-lows-wintrust-213904747.html","publishedAt":"2026-06-18"},{"title":"2 Momentum  Stocks Worth Investigating and 1 Facing Challenges","publisher":"StockStory","link":"https://finance.yahoo.com/markets/stocks/articles/2-momentum-stocks-worth-investigating-133320033.html","publishedAt":"2026-06-12"},{"title":"First Financial Bancorp. (FFBC) Hits Fresh High: Is There Still Room to Run?","publisher":"Zacks","link":"https://finance.yahoo.com/markets/stocks/articles/first-financial-bancorp-ffbc-hits-131503683.html","publishedAt":"2026-06-10"},{"title":"Wintrust Financial (WTFC) Valuation Check After Recent Share Performance And DCF Undervaluation Signal","publisher":"Simply Wall St.","link":"https://finance.yahoo.com/markets/stocks/articles/wintrust-financial-wtfc-valuation-check-081417917.html","publishedAt":"2026-06-01"},{"title":"Wintrust (WTFC) Moves to Buy: Rationale Behind the Upgrade","publisher":"Zacks","link":"https://finance.yahoo.com/markets/stocks/articles/wintrust-wtfc-moves-buy-rationale-160002294.html","publishedAt":"2026-05-26"},{"title":"1 Small-Cap Stock to Consider Right Now and 2 We Ignore","publisher":"StockStory","link":"https://finance.yahoo.com/markets/stocks/articles/1-small-cap-stock-consider-030055446.html","publishedAt":"2026-05-21"},{"title":"Bank of Hawaii, Glacier Bancorp, and Wintrust Financial Shares Plummet, What You Need To Know","publisher":"StockStory","link":"https://finance.yahoo.com/markets/stocks/articles/bank-hawaii-glacier-bancorp-wintrust-022855356.html","publishedAt":"2026-05-16"}],"ticker":"WTFC","company":"Wintrust Financial Corporation","historySource":"snapshot","earningsHistory":[{"date":"2023-07-19","epsActual":2.38,"epsEstimate":2.4,"surprisePct":-0.78},{"date":"2023-10-17","epsActual":2.53,"epsEstimate":2.41,"surprisePct":4.95},{"date":"2024-01-17","epsActual":1.87,"epsEstimate":2.52,"surprisePct":-25.84},{"date":"2024-04-17","epsActual":2.89,"epsEstimate":2.44,"surprisePct":18.64},{"date":"2024-07-17","epsActual":2.32,"epsEstimate":2.42,"surprisePct":-3.99},{"date":"2024-10-21","epsActual":2.47,"epsEstimate":2.51,"surprisePct":-1.57},{"date":"2025-01-21","epsActual":2.63,"epsEstimate":2.47,"surprisePct":6.35},{"date":"2025-04-21","epsActual":2.69,"epsEstimate":2.49,"surprisePct":8.14},{"date":"2025-07-21","epsActual":2.82,"epsEstimate":2.62,"surprisePct":7.83},{"date":"2025-10-20","epsActual":3.06,"epsEstimate":2.71,"surprisePct":12.85},{"date":"2026-01-20","epsActual":3.15,"epsEstimate":2.93,"surprisePct":7.47},{"date":"2026-04-20","epsActual":3.22,"epsEstimate":2.95,"surprisePct":9.15}]}