{"fundamentals":{"marketCapB":0.275,"targetPrice":4.5613,"avgVolume":372560.0,"volume":206612.0,"prevClose":3.21,"week52High":5.55,"week52Low":2.57,"exchange":"NYQ","epsTtm":-0.35,"epsNextY":0.1311,"salesB":2.671,"grossProfitB":1.585,"incomeB":-0.191,"cashB":4.28,"debtB":0.027,"profitMargin":-7.16,"grossMargin":59.34,"operMargin":-9.65,"roe":-4.85,"currentRatio":3.78,"quickRatio":3.71,"forwardPE":24.18,"sharesB":0.088,"ps":0.1,"source":"nasdaq+yahoo"},"news":[{"title":"Zhihu Inc. to Hold Annual General Meeting on June 30, 2026","publisher":"GlobeNewswire","link":"https://finance.yahoo.com/markets/stocks/articles/zhihu-inc-hold-annual-general-115800163.html","publishedAt":"2026-06-08"},{"title":"Zhihu Inc. (NYSE:ZH) Just Reported First-Quarter Earnings: Have Analysts Changed Their Mind On The Stock?","publisher":"Simply Wall St.","link":"https://finance.yahoo.com/markets/stocks/articles/zhihu-inc-nyse-zh-just-130040343.html","publishedAt":"2026-06-06"},{"title":"3 Promising Penny Stocks With Market Caps Reaching $300M","publisher":"Simply Wall St.","link":"https://finance.yahoo.com/markets/stocks/articles/3-promising-penny-stocks-market-180747092.html","publishedAt":"2026-06-05"},{"title":"Zhihu Inc (ZH) Q1 2026 Earnings Call Highlights: Strong Start to 2026 with AI Integration and ...","publisher":"GuruFocus.com","link":"https://finance.yahoo.com/markets/stocks/articles/zhihu-inc-zh-q1-2026-190025885.html","publishedAt":"2026-06-04"},{"title":"Zhihu Q1 Earnings Call Highlights","publisher":"MarketBeat","link":"https://finance.yahoo.com/m/bbf2032f-45a3-3456-9ec5-5a52f66ddaa3/zhihu-q1-earnings-call.html","publishedAt":"2026-06-03"},{"title":"Zhihu Inc. Reports Unaudited First Quarter 2026 Financial Results","publisher":"GlobeNewswire","link":"https://finance.yahoo.com/markets/stocks/articles/zhihu-inc-reports-unaudited-first-091000653.html","publishedAt":"2026-06-03"},{"title":"Zhihu Inc. Announces Change of Non-Executive Director","publisher":"GlobeNewswire","link":"https://finance.yahoo.com/markets/stocks/articles/zhihu-inc-announces-change-non-090000939.html","publishedAt":"2026-06-03"},{"title":"Zhihu Inc. to Report First Quarter 2026 Financial Results on June 3, 2026","publisher":"GlobeNewswire","link":"https://finance.yahoo.com/markets/stocks/articles/zhihu-inc-report-first-quarter-102000387.html","publishedAt":"2026-05-11"}],"ticker":"ZH","company":"Zhihu Inc. American Depositary Shares each representing three (3) Class A Ordinary Shares","historySource":"snapshot"}